pychatwork/__init__.py
pychatwork-1.0.5.dist-info/WHEEL
pychatwork-1.0.5.dist-info/METADATA
pychatwork-1.0.5.dist-info/RECORD
